bin/plastes
plastes/__init__.py
plastes/build.py
plastes/server.py
plastes/include/atom-one-light.css
plastes/include/base.css
plastes/include/highlight.js
plastes/include/position-images.js
plastes-0.0.1.data/scripts/plastes
plastes-0.0.1.dist-info/LICENSE
plastes-0.0.1.dist-info/METADATA
plastes-0.0.1.dist-info/WHEEL
plastes-0.0.1.dist-info/top_level.txt
plastes-0.0.1.dist-info/RECORD
