Metadata-Version: 2.1
Name: plastes
Version: 0.0.1
Summary: A simple and extensible static blog post builder.
Author-email: Nathan Yan <nathancy@uw.edu>
License: Copyright (c) 2022 Nathan Yan        
Project-URL: Homepage, https://github.com/nathan-yan/plastes
Classifier: Programming Language :: Python :: 3
Classifier: License :: OSI Approved :: MIT License
Classifier: Operating System :: OS Independent
Requires-Python: >=3.9
License-File: LICENSE
Requires-Dist: PyYAML (>=6.0)
Requires-Dist: watchdog (>=2.1.9)
Requires-Dist: mistletoe (>=0.9.0)
Requires-Dist: dominate (>=2.7.0)
